{
  "products": [
    {
      "title": "Produto de Testes",
      "id": "1"
    },
    {
      "id": "6507",
      "title": "João Luiz"
    },
    {
      "id": "bd2c",
      "title": "Max Verstappen"
    },
    {
      "id": "8e61",
      "title": "Livro Código Limpo"
    },
    {
      "id": "1624",
      "title": "Guitarra"
    },
    {
      "id": "0994",
      "title": "Caneta"
    },
    {
      "id": "1515",
      "title": "boneco"
    },
    {
      "id": "ac5f",
      "title": "Teclado"
    }
  ]
}